labeless/VERSION
labeless/__init__.py
labeless/logs.py
labeless/pehelper.py
labeless/pehelper_decl.py
labeless/py_olly.py
labeless/pyexcore.py
labeless/rdebug.py
labeless/rpc_pb2.py
labeless/watchdog.py
labeless/backend/__init__.py
labeless/backend/ollydbg11/__init__.py
labeless/backend/ollydbg11/ollyapi.py
labeless/backend/ollydbg11/ollyutils.py
labeless/backend/ollydbg20/__init__.py
labeless/backend/ollydbg20/breakpoints.py
labeless/backend/ollydbg20/memory.py
labeless/backend/ollydbg20/ollyapi2.py
labeless/backend/ollydbg20/ollyutils.py
labeless/backend/ollydbg20/sym.py
labeless/backend/ollydbg20/threads.py
labeless/backend/ollydbg20/utils.py
labeless/backend/x64dbg/__init__.py
labeless/backend/x64dbg/_plugins.py
labeless/backend/x64dbg/api.py
labeless/backend/x64dbg/bridgemain.py
labeless/backend/x64dbg/scriptapi.py
labeless/backend/x64dbg/utils.py
labeless/backend/x64dbg/x64dbgapi.py
labeless/backend/x64dbg/x64dbgapi64.py
labeless-1.1.7.0.dist-info/METADATA
labeless-1.1.7.0.dist-info/WHEEL
labeless-1.1.7.0.dist-info/top_level.txt
labeless-1.1.7.0.dist-info/RECORD
