Metadata-Version: 2.1
Name: labeless
Version: 1.1.7.0
Summary: Labels/Comments synchronization between IDA PRO and dbg backend (OllyDbg1.10, OllyDbg 2.01, x64dbg) , Remote memory dumping tool (including x64-bit), Python scripting tool
Home-page: https://github.com/a1ext/labeless
Author: Aliaksandr Trafimchuk
Author-email: a13x4nd3r.t@gmail.com
License: CC-BY-NC-4.0
Keywords: labeless,IDA PRO,OllyDbg,x64dbg,dumping,tracing,strings decryption,API resolving
Platform: UNKNOWN
Classifier: Operating System :: OS Independent
Classifier: Programming Language :: Python :: 3.10
Classifier: Topic :: Security
Classifier: Topic :: Software Development :: Debuggers
Classifier: Topic :: Software Development :: Disassemblers
Classifier: Topic :: Utilities
Requires-Dist: setuptools
Requires-Dist: protobuf (==3.20.3)
